ghproject/GitHubAPI.py
ghproject/__init__.py
ghproject/__version__.py
ghproject/api_calls.py
ghproject/arg_parser.py
ghproject/logging_functions.py
ghproject/md_functions.py
ghproject/upload_project.py
ghproject-0.0.2.dist-info/LICENSE
ghproject-0.0.2.dist-info/METADATA
ghproject-0.0.2.dist-info/WHEEL
ghproject-0.0.2.dist-info/top_level.txt
ghproject-0.0.2.dist-info/RECORD
